{
  "GUID": "176bc4",
  "Name": "Infinite_Bag",
  "Transform": {
    "posX": -34.0,
    "posY": 0.913001239,
    "posZ": -27.0,
    "rotX": -1.2927336E-07,
    "rotY": 179.980057,
    "rotZ": 3.21366883E-06,
    "scaleX": 1.0,
    "scaleY": 1.0,
    "scaleZ": 1.0
  },
  "Nickname": "d6",
  "Description": "",
  "GMNotes": "",
  "AltLookAngle": {
    "x": 0.0,
    "y": 0.0,
    "z": 0.0
  },
  "ColorDiffuse": {
    "r": 1.0,
    "g": 1.0,
    "b": 1.0
  },
  "LayoutGroupSortIndex": 0,
  "Value": 0,
  "Locked": true,
  "Grid": true,
  "Snap": true,
  "IgnoreFoW": false,
  "MeasureMovement": false,
  "DragSelectable": true,
  "Autoraise": true,
  "Sticky": true,
  "Tooltip": true,
  "GridProjection": false,
  "HideWhenFaceDown": false,
  "Hands": false,
  "MaterialIndex": -1,
  "MeshIndex": -1
}